pyexport/__init__.py
pyexport/code.py
pyexport/html.py
pyexport/pdf.py
pyexport/serialize.py
pyexport/sql.py
tests/__init__.py
PyExport-0.0.0.dist-info/LICENSE
PyExport-0.0.0.dist-info/METADATA
PyExport-0.0.0.dist-info/WHEEL
PyExport-0.0.0.dist-info/top_level.txt
PyExport-0.0.0.dist-info/RECORD
