Metadata-Version: 2.1
Name: PyExport
Version: 0.0.0
Summary: Export data programatically to emails, html, pdf, docs, xls, etc.
Home-page: https://github.com/sonal-raj/PyExport
Author: Sonal Raj
Author-email: sonal.nitjsr@gmail.com
License: UNKNOWN
Platform: UNKNOWN
Classifier: Programming Language :: Python :: 3
Classifier: License :: OSI Approved :: MIT License
Classifier: Operating System :: OS Independent
